{
  "annotations": {
    "list": [
      {
        "builtIn": 1,
        "datasource": "-- Grafana --",
        "enable": true,
        "hide": true,
        "iconColor": "rgba(0, 211, 255, 1)",
        "name": "Annotations & Alerts",
        "target": {
          "limit": 100,
          "matchAny": false,
          "tags": [],
          "type": "dashboard"
        },
        "type": "dashboard"
      }
    ]
  },
  "editable": true,
  "fiscalYearStartMonth": 0,
  "graphTooltip": 0,
  "id": 1,
  "links": [],
  "liveNow": false,
  "panels": [
    {
      "fieldConfig": {
        "defaults": {
          "color": {
            "mode": "thresholds"
          },
          "mappings": [],
          "thresholds": {
            "mode": "absolute",
            "steps": [
              {
                "color": "light-red",
                "value": null
              },
              {
                "color": "red",
                "value": 80
              }
            ]
          },
          "unit": "kwatth"
        },
        "overrides": []
      },
      "gridPos": {
        "h": 3,
        "w": 4,
        "x": 0,
        "y": 0
      },
      "id": 9,
      "options": {
        "colorMode": "value",
        "graphMode": "none",
        "justifyMode": "auto",
        "orientation": "auto",
        "reduceOptions": {
          "calcs": [
            "lastNotNull"
          ],
          "fields": "",
          "values": false
        },
        "textMode": "auto"
      },
      "pluginVersion": "8.4.2",
      "targets": [
        {
          "datasource": {
            "type": "influxdb",
            "uid": "pAmt_nkRk"
          },
          "groupBy": [
            {
              "params": [
                "$__interval"
              ],
              "type": "time"
            },
            {
              "params": [
                "null"
              ],
              "type": "fill"
            }
          ],
          "measurement": "energy",
          "orderByTime": "ASC",
          "policy": "default",
          "refId": "A",
          "resultFormat": "time_series",
          "select": [
            [
              {
                "params": [
                  "total_active_energy"
                ],
                "type": "field"
              },
              {
                "params": [],
                "type": "last"
              }
            ]
          ],
          "tags": [
            {
              "key": "location",
              "operator": "=",
              "value": "common"
            }
          ]
        }
      ],
      "title": "Consumi totali",
      "type": "stat"
    },
    {
      "fieldConfig": {
        "defaults": {
          "color": {
            "mode": "thresholds"
          },
          "mappings": [],
          "thresholds": {
            "mode": "absolute",
            "steps": [
              {
                "color": "light-orange",
                "value": null
              },
              {
                "color": "red",
                "value": 80
              }
            ]
          },
          "unit": "kwatth"
        },
        "overrides": []
      },
      "gridPos": {
        "h": 3,
        "w": 4,
        "x": 4,
        "y": 0
      },
      "id": 12,
      "options": {
        "colorMode": "value",
        "graphMode": "none",
        "justifyMode": "auto",
        "orientation": "auto",
        "reduceOptions": {
          "calcs": [
            "lastNotNull"
          ],
          "fields": "",
          "values": false
        },
        "textMode": "auto"
      },
      "pluginVersion": "8.4.2",
      "targets": [
        {
          "datasource": {
            "type": "influxdb",
            "uid": "pAmt_nkRk"
          },
          "groupBy": [
            {
              "params": [
                "$__interval"
              ],
              "type": "time"
            },
            {
              "params": [
                "null"
              ],
              "type": "fill"
            }
          ],
          "measurement": "energy",
          "orderByTime": "ASC",
          "policy": "default",
          "query": "SELECT (last(\"total_active_energy\") - first(\"total_active_energy\")) FROM \"energy\" WHERE (\"location\" = 'common') AND time >= now() - 30d and time <= now() ",
          "rawQuery": true,
          "refId": "A",
          "resultFormat": "time_series",
          "select": [
            [
              {
                "params": [
                  "total_active_energy"
                ],
                "type": "field"
              },
              {
                "params": [],
                "type": "last"
              }
            ]
          ],
          "tags": [
            {
              "key": "location",
              "operator": "=",
              "value": "common"
            }
          ]
        }
      ],
      "title": "Consumi ultimo mese",
      "type": "stat"
    },
    {
      "fieldConfig": {
        "defaults": {
          "color": {
            "mode": "thresholds"
          },
          "mappings": [],
          "thresholds": {
            "mode": "absolute",
            "steps": [
              {
                "color": "light-blue",
                "value": null
              },
              {
                "color": "red",
                "value": 80
              }
            ]
          },
          "unit": "kwatth"
        },
        "overrides": []
      },
      "gridPos": {
        "h": 3,
        "w": 4,
        "x": 8,
        "y": 0
      },
      "id": 8,
      "options": {
        "colorMode": "value",
        "graphMode": "none",
        "justifyMode": "auto",
        "orientation": "auto",
        "reduceOptions": {
          "calcs": [
            "delta"
          ],
          "fields": "",
          "values": false
        },
        "textMode": "auto"
      },
      "pluginVersion": "8.4.2",
      "targets": [
        {
          "datasource": {
            "type": "influxdb",
            "uid": "pAmt_nkRk"
          },
          "groupBy": [
            {
              "params": [
                "$__interval"
              ],
              "type": "time"
            },
            {
              "params": [
                "null"
              ],
              "type": "fill"
            }
          ],
          "measurement": "energy",
          "orderByTime": "ASC",
          "policy": "default",
          "refId": "A",
          "resultFormat": "time_series",
          "select": [
            [
              {
                "params": [
                  "total_active_energy"
                ],
                "type": "field"
              },
              {
                "params": [],
                "type": "last"
              }
            ]
          ],
          "tags": [
            {
              "key": "location",
              "operator": "=",
              "value": "common"
            }
          ]
        }
      ],
      "title": "Consumi intervallo",
      "type": "stat"
    },
    {
      "fieldConfig": {
        "defaults": {
          "color": {
            "mode": "thresholds"
          },
          "mappings": [],
          "thresholds": {
            "mode": "absolute",
            "steps": [
              {
                "color": "dark-green",
                "value": null
              },
              {
                "color": "red",
                "value": 80
              }
            ]
          },
          "unit": "kwatth"
        },
        "overrides": []
      },
      "gridPos": {
        "h": 3,
        "w": 4,
        "x": 12,
        "y": 0
      },
      "id": 10,
      "options": {
        "colorMode": "value",
        "graphMode": "none",
        "justifyMode": "auto",
        "orientation": "auto",
        "reduceOptions": {
          "calcs": [
            "lastNotNull"
          ],
          "fields": "",
          "values": false
        },
        "textMode": "auto"
      },
      "pluginVersion": "8.4.2",
      "targets": [
        {
          "datasource": {
            "type": "influxdb",
            "uid": "pAmt_nkRk"
          },
          "groupBy": [
            {
              "params": [
                "$__interval"
              ],
              "type": "time"
            },
            {
              "params": [
                "null"
              ],
              "type": "fill"
            }
          ],
          "measurement": "energy",
          "orderByTime": "ASC",
          "policy": "default",
          "query": "SELECT (last(\"total_active_energy\") - first(\"total_active_energy\")) FROM \"energy\" WHERE (\"location\" = 'common') AND time >= now() - 1h and time <= now() ",
          "rawQuery": true,
          "refId": "A",
          "resultFormat": "time_series",
          "select": [
            [
              {
                "params": [
                  "total_active_energy"
                ],
                "type": "field"
              },
              {
                "params": [],
                "type": "last"
              }
            ]
          ],
          "tags": [
            {
              "key": "location",
              "operator": "=",
              "value": "common"
            }
          ]
        }
      ],
      "title": "Consumi ultima ora",
      "type": "stat"
    },
    {
      "fieldConfig": {
        "defaults": {
          "color": {
            "mode": "thresholds"
          },
          "mappings": [],
          "thresholds": {
            "mode": "absolute",
            "steps": [
              {
                "color": "light-purple",
                "value": null
              },
              {
                "color": "red",
                "value": 80
              }
            ]
          },
          "unit": "kwatth"
        },
        "overrides": []
      },
      "gridPos": {
        "h": 3,
        "w": 4,
        "x": 16,
        "y": 0
      },
      "id": 13,
      "options": {
        "colorMode": "value",
        "graphMode": "none",
        "justifyMode": "auto",
        "orientation": "auto",
        "reduceOptions": {
          "calcs": [
            "lastNotNull"
          ],
          "fields": "",
          "values": false
        },
        "textMode": "auto"
      },
      "pluginVersion": "8.4.2",
      "targets": [
        {
          "datasource": {
            "type": "influxdb",
            "uid": "pAmt_nkRk"
          },
          "groupBy": [
            {
              "params": [
                "$__interval"
              ],
              "type": "time"
            },
            {
              "params": [
                "null"
              ],
              "type": "fill"
            }
          ],
          "measurement": "energy",
          "orderByTime": "ASC",
          "policy": "default",
          "query": "SELECT (last(\"total_active_energy\") - first(\"total_active_energy\")) FROM \"energy\" WHERE (\"location\" = 'common') AND time >= now() - 1d and time <= now() ",
          "rawQuery": true,
          "refId": "A",
          "resultFormat": "time_series",
          "select": [
            [
              {
                "params": [
                  "total_active_energy"
                ],
                "type": "field"
              },
              {
                "params": [],
                "type": "last"
              }
            ]
          ],
          "tags": [
            {
              "key": "location",
              "operator": "=",
              "value": "common"
            }
          ]
        }
      ],
      "title": "Consumi ultimo giorno",
      "type": "stat"
    },
    {
      "fieldConfig": {
        "defaults": {
          "color": {
            "mode": "thresholds"
          },
          "mappings": [],
          "thresholds": {
            "mode": "absolute",
            "steps": [
              {
                "color": "light-yellow",
                "value": null
              },
              {
                "color": "red",
                "value": 80
              }
            ]
          },
          "unit": "kwatth"
        },
        "overrides": []
      },
      "gridPos": {
        "h": 3,
        "w": 4,
        "x": 20,
        "y": 0
      },
      "id": 11,
      "options": {
        "colorMode": "value",
        "graphMode": "none",
        "justifyMode": "auto",
        "orientation": "auto",
        "reduceOptions": {
          "calcs": [
            "lastNotNull"
          ],
          "fields": "",
          "values": false
        },
        "textMode": "auto"
      },
      "pluginVersion": "8.4.2",
      "targets": [
        {
          "datasource": {
            "type": "influxdb",
            "uid": "pAmt_nkRk"
          },
          "groupBy": [
            {
              "params": [
                "$__interval"
              ],
              "type": "time"
            },
            {
              "params": [
                "null"
              ],
              "type": "fill"
            }
          ],
          "measurement": "energy",
          "orderByTime": "ASC",
          "policy": "default",
          "query": "SELECT (last(\"total_active_energy\") - first(\"total_active_energy\")) FROM \"energy\" WHERE (\"location\" = 'common') AND time >= now() - 7d and time <= now() ",
          "rawQuery": true,
          "refId": "A",
          "resultFormat": "time_series",
          "select": [
            [
              {
                "params": [
                  "total_active_energy"
                ],
                "type": "field"
              },
              {
                "params": [],
                "type": "last"
              }
            ]
          ],
          "tags": [
            {
              "key": "location",
              "operator": "=",
              "value": "common"
            }
          ]
        }
      ],
      "title": "Consumi ultima settimana",
      "type": "stat"
    },
    {
      "fieldConfig": {
        "defaults": {
          "color": {
            "mode": "palette-classic"
          },
          "custom": {
            "axisLabel": "",
            "axisPlacement": "auto",
            "barAlignment": 0,
            "drawStyle": "line",
            "fillOpacity": 0,
            "gradientMode": "none",
            "hideFrom": {
              "legend": false,
              "tooltip": false,
              "viz": false
            },
            "lineInterpolation": "linear",
            "lineWidth": 1,
            "pointSize": 5,
            "scaleDistribution": {
              "type": "linear"
            },
            "showPoints": "auto",
            "spanNulls": false,
            "stacking": {
              "group": "A",
              "mode": "none"
            },
            "thresholdsStyle": {
              "mode": "off"
            }
          },
          "mappings": [],
          "thresholds": {
            "mode": "absolute",
            "steps": [
              {
                "color": "green",
                "value": null
              },
              {
                "color": "red",
                "value": 80
              }
            ]
          },
          "unit": "watt"
        },
        "overrides": []
      },
      "gridPos": {
        "h": 6,
        "w": 24,
        "x": 0,
        "y": 3
      },
      "id": 2,
      "options": {
        "legend": {
          "calcs": [
            "last",
            "mean",
            "min",
            "max"
          ],
          "displayMode": "list",
          "placement": "bottom"
        },
        "tooltip": {
          "mode": "single",
          "sort": "none"
        }
      },
      "targets": [
        {
          "alias": "active power",
          "datasource": {
            "type": "influxdb",
            "uid": "pAmt_nkRk"
          },
          "groupBy": [
            {
              "params": [
                "$interval"
              ],
              "type": "time"
            },
            {
              "params": [
                "linear"
              ],
              "type": "fill"
            }
          ],
          "measurement": "energy",
          "orderByTime": "ASC",
          "policy": "default",
          "refId": "A",
          "resultFormat": "time_series",
          "select": [
            [
              {
                "params": [
                  "active_power"
                ],
                "type": "field"
              },
              {
                "params": [],
                "type": "last"
              }
            ]
          ],
          "tags": [
            {
              "key": "location",
              "operator": "=",
              "value": "common"
            }
          ]
        },
        {
          "alias": "reactive power",
          "datasource": {
            "type": "influxdb",
            "uid": "pAmt_nkRk"
          },
          "groupBy": [
            {
              "params": [
                "$interval"
              ],
              "type": "time"
            },
            {
              "params": [
                "linear"
              ],
              "type": "fill"
            }
          ],
          "hide": false,
          "measurement": "energy",
          "orderByTime": "ASC",
          "policy": "default",
          "refId": "B",
          "resultFormat": "time_series",
          "select": [
            [
              {
                "params": [
                  "reactive_power"
                ],
                "type": "field"
              },
              {
                "params": [],
                "type": "last"
              },
              {
                "params": [
                  " * 1000"
                ],
                "type": "math"
              }
            ]
          ],
          "tags": [
            {
              "key": "location",
              "operator": "=",
              "value": "common"
            }
          ]
        }
      ],
      "title": "Potenza istantanea",
      "type": "timeseries"
    },
    {
      "fieldConfig": {
        "defaults": {
          "color": {
            "mode": "palette-classic"
          },
          "custom": {
            "axisLabel": "",
            "axisPlacement": "auto",
            "barAlignment": 0,
            "drawStyle": "line",
            "fillOpacity": 0,
            "gradientMode": "none",
            "hideFrom": {
              "legend": false,
              "tooltip": false,
              "viz": false
            },
            "lineInterpolation": "linear",
            "lineWidth": 1,
            "pointSize": 5,
            "scaleDistribution": {
              "type": "linear"
            },
            "showPoints": "auto",
            "spanNulls": false,
            "stacking": {
              "group": "A",
              "mode": "none"
            },
            "thresholdsStyle": {
              "mode": "off"
            }
          },
          "mappings": [],
          "thresholds": {
            "mode": "absolute",
            "steps": [
              {
                "color": "green",
                "value": null
              },
              {
                "color": "red",
                "value": 80
              }
            ]
          },
          "unit": "volt"
        },
        "overrides": [
          {
            "matcher": {
              "id": "byName",
              "options": "energy.last"
            },
            "properties": [
              {
                "id": "color",
                "value": {
                  "fixedColor": "orange",
                  "mode": "fixed"
                }
              }
            ]
          },
          {
            "matcher": {
              "id": "byName",
              "options": "voltage"
            },
            "properties": [
              {
                "id": "color",
                "value": {
                  "fixedColor": "red",
                  "mode": "fixed"
                }
              }
            ]
          }
        ]
      },
      "gridPos": {
        "h": 5,
        "w": 12,
        "x": 0,
        "y": 9
      },
      "id": 15,
      "options": {
        "legend": {
          "calcs": [
            "last",
            "mean"
          ],
          "displayMode": "list",
          "placement": "bottom"
        },
        "tooltip": {
          "mode": "single",
          "sort": "none"
        }
      },
      "targets": [
        {
          "alias": "voltage",
          "datasource": {
            "type": "influxdb",
            "uid": "pAmt_nkRk"
          },
          "groupBy": [
            {
              "params": [
                "$__interval"
              ],
              "type": "time"
            },
            {
              "params": [
                "linear"
              ],
              "type": "fill"
            }
          ],
          "measurement": "energy",
          "orderByTime": "ASC",
          "policy": "default",
          "refId": "A",
          "resultFormat": "time_series",
          "select": [
            [
              {
                "params": [
                  "voltage"
                ],
                "type": "field"
              },
              {
                "params": [],
                "type": "last"
              }
            ]
          ],
          "tags": [
            {
              "key": "location",
              "operator": "=",
              "value": "common"
            }
          ]
        }
      ],
      "title": "Tensione",
      "type": "timeseries"
    },
    {
      "fieldConfig": {
        "defaults": {
          "color": {
            "mode": "palette-classic"
          },
          "custom": {
            "axisLabel": "",
            "axisPlacement": "auto",
            "barAlignment": 0,
            "drawStyle": "line",
            "fillOpacity": 0,
            "gradientMode": "none",
            "hideFrom": {
              "legend": false,
              "tooltip": false,
              "viz": false
            },
            "lineInterpolation": "linear",
            "lineWidth": 1,
            "pointSize": 5,
            "scaleDistribution": {
              "type": "linear"
            },
            "showPoints": "auto",
            "spanNulls": false,
            "stacking": {
              "group": "A",
              "mode": "none"
            },
            "thresholdsStyle": {
              "mode": "off"
            }
          },
          "mappings": [],
          "thresholds": {
            "mode": "absolute",
            "steps": [
              {
                "color": "green",
                "value": null
              },
              {
                "color": "red",
                "value": 80
              }
            ]
          },
          "unit": "amp"
        },
        "overrides": [
          {
            "matcher": {
              "id": "byName",
              "options": "energy.last"
            },
            "properties": [
              {
                "id": "color",
                "value": {
                  "fixedColor": "orange",
                  "mode": "fixed"
                }
              }
            ]
          },
          {
            "matcher": {
              "id": "byName",
              "options": "current"
            },
            "properties": [
              {
                "id": "color",
                "value": {
                  "fixedColor": "orange",
                  "mode": "fixed"
                }
              }
            ]
          }
        ]
      },
      "gridPos": {
        "h": 5,
        "w": 12,
        "x": 12,
        "y": 9
      },
      "id": 4,
      "options": {
        "legend": {
          "calcs": [
            "last",
            "mean"
          ],
          "displayMode": "list",
          "placement": "bottom"
        },
        "tooltip": {
          "mode": "single",
          "sort": "none"
        }
      },
      "targets": [
        {
          "alias": "current",
          "datasource": {
            "type": "influxdb",
            "uid": "pAmt_nkRk"
          },
          "groupBy": [
            {
              "params": [
                "$__interval"
              ],
              "type": "time"
            },
            {
              "params": [
                "linear"
              ],
              "type": "fill"
            }
          ],
          "measurement": "energy",
          "orderByTime": "ASC",
          "policy": "default",
          "refId": "A",
          "resultFormat": "time_series",
          "select": [
            [
              {
                "params": [
                  "current"
                ],
                "type": "field"
              },
              {
                "params": [],
                "type": "last"
              }
            ]
          ],
          "tags": [
            {
              "key": "location",
              "operator": "=",
              "value": "common"
            }
          ]
        }
      ],
      "title": "Corrente",
      "type": "timeseries"
    },
    {
      "description": "",
      "fieldConfig": {
        "defaults": {
          "color": {
            "mode": "palette-classic"
          },
          "custom": {
            "axisLabel": "",
            "axisPlacement": "auto",
            "barAlignment": 0,
            "drawStyle": "line",
            "fillOpacity": 0,
            "gradientMode": "none",
            "hideFrom": {
              "legend": false,
              "tooltip": false,
              "viz": false
            },
            "lineInterpolation": "linear",
            "lineWidth": 1,
            "pointSize": 5,
            "scaleDistribution": {
              "type": "linear"
            },
            "showPoints": "auto",
            "spanNulls": 3600000,
            "stacking": {
              "group": "A",
              "mode": "none"
            },
            "thresholdsStyle": {
              "mode": "off"
            }
          },
          "mappings": [],
          "thresholds": {
            "mode": "absolute",
            "steps": [
              {
                "color": "green",
                "value": null
              },
              {
                "color": "red",
                "value": 80
              }
            ]
          },
          "unit": "hertz"
        },
        "overrides": [
          {
            "matcher": {
              "id": "byName",
              "options": "energy.last"
            },
            "properties": [
              {
                "id": "color",
                "value": {
                  "fixedColor": "red",
                  "mode": "fixed"
                }
              }
            ]
          },
          {
            "matcher": {
              "id": "byName",
              "options": "frequency"
            },
            "properties": [
              {
                "id": "color",
                "value": {
                  "fixedColor": "blue",
                  "mode": "fixed"
                }
              }
            ]
          }
        ]
      },
      "gridPos": {
        "h": 5,
        "w": 12,
        "x": 0,
        "y": 14
      },
      "id": 14,
      "options": {
        "legend": {
          "calcs": [
            "last",
            "mean"
          ],
          "displayMode": "list",
          "placement": "bottom"
        },
        "tooltip": {
          "mode": "single",
          "sort": "none"
        }
      },
      "targets": [
        {
          "alias": "frequency",
          "datasource": {
            "type": "influxdb",
            "uid": "pAmt_nkRk"
          },
          "groupBy": [
            {
              "params": [
                "1m"
              ],
              "type": "time"
            },
            {
              "params": [
                "linear"
              ],
              "type": "fill"
            }
          ],
          "measurement": "energy",
          "orderByTime": "ASC",
          "policy": "default",
          "refId": "A",
          "resultFormat": "time_series",
          "select": [
            [
              {
                "params": [
                  "freq"
                ],
                "type": "field"
              },
              {
                "params": [],
                "type": "mean"
              }
            ]
          ],
          "tags": [
            {
              "key": "location",
              "operator": "=",
              "value": "common"
            }
          ]
        }
      ],
      "title": "Frequenza",
      "type": "timeseries"
    },
    {
      "fieldConfig": {
        "defaults": {
          "color": {
            "mode": "palette-classic"
          },
          "custom": {
            "axisLabel": "",
            "axisPlacement": "auto",
            "barAlignment": 0,
            "drawStyle": "line",
            "fillOpacity": 0,
            "gradientMode": "none",
            "hideFrom": {
              "legend": false,
              "tooltip": false,
              "viz": false
            },
            "lineInterpolation": "linear",
            "lineWidth": 1,
            "pointSize": 5,
            "scaleDistribution": {
              "type": "linear"
            },
            "showPoints": "auto",
            "spanNulls": false,
            "stacking": {
              "group": "A",
              "mode": "none"
            },
            "thresholdsStyle": {
              "mode": "off"
            }
          },
          "mappings": [],
          "thresholds": {
            "mode": "absolute",
            "steps": [
              {
                "color": "green",
                "value": null
              },
              {
                "color": "red",
                "value": 80
              }
            ]
          },
          "unit": "amp"
        },
        "overrides": [
          {
            "matcher": {
              "id": "byName",
              "options": "energy.last"
            },
            "properties": [
              {
                "id": "color",
                "value": {
                  "fixedColor": "orange",
                  "mode": "fixed"
                }
              }
            ]
          },
          {
            "matcher": {
              "id": "byName",
              "options": "current"
            },
            "properties": [
              {
                "id": "color",
                "value": {
                  "fixedColor": "blue",
                  "mode": "fixed"
                }
              }
            ]
          },
          {
            "matcher": {
              "id": "byName",
              "options": "power factor"
            },
            "properties": [
              {
                "id": "color",
                "value": {
                  "fixedColor": "purple",
                  "mode": "fixed"
                }
              }
            ]
          }
        ]
      },
      "gridPos": {
        "h": 5,
        "w": 12,
        "x": 12,
        "y": 14
      },
      "id": 16,
      "options": {
        "legend": {
          "calcs": [
            "last",
            "mean"
          ],
          "displayMode": "list",
          "placement": "bottom"
        },
        "tooltip": {
          "mode": "single",
          "sort": "none"
        }
      },
      "targets": [
        {
          "alias": "power factor",
          "datasource": {
            "type": "influxdb",
            "uid": "pAmt_nkRk"
          },
          "groupBy": [
            {
              "params": [
                "$__interval"
              ],
              "type": "time"
            },
            {
              "params": [
                "linear"
              ],
              "type": "fill"
            }
          ],
          "measurement": "energy",
          "orderByTime": "ASC",
          "policy": "default",
          "refId": "A",
          "resultFormat": "time_series",
          "select": [
            [
              {
                "params": [
                  "current"
                ],
                "type": "field"
              },
              {
                "params": [],
                "type": "last"
              }
            ]
          ],
          "tags": [
            {
              "key": "location",
              "operator": "=",
              "value": "common"
            }
          ]
        }
      ],
      "title": "Fattore di potenza",
      "type": "timeseries"
    }
  ],
  "refresh": "5s",
  "schemaVersion": 35,
  "style": "dark",
  "tags": [],
  "templating": {
    "list": []
  },
  "time": {
    "from": "now-6h",
    "to": "now"
  },
  "timepicker": {},
  "timezone": "",
  "title": "dommu",
  "uid": "4XPwznkgk",
  "version": 25,
  "weekStart": ""
}